cloudera/airflow/providers/__init__.py
cloudera/airflow/providers/hooks/__init__.py
cloudera/airflow/providers/hooks/cde.py
cloudera/airflow/providers/hooks/cde_hook.py
cloudera/airflow/providers/hooks/cdw.py
cloudera/airflow/providers/hooks/cdw_hook.py
cloudera/airflow/providers/model/__init__.py
cloudera/airflow/providers/model/connection.py
cloudera/airflow/providers/operators/__init__.py
cloudera/airflow/providers/operators/cde.py
cloudera/airflow/providers/operators/cde_operator.py
cloudera/airflow/providers/operators/cdw.py
cloudera/airflow/providers/operators/cdw_operator.py
cloudera/airflow/providers/sensors/__init__.py
cloudera/airflow/providers/sensors/cdw.py
cloudera/airflow/providers/sensors/cdw_sensor.py
cloudera/cdp/airflow/__init__.py
cloudera/cdp/airflow/hooks/__init__.py
cloudera/cdp/airflow/hooks/cde_hook.py
cloudera/cdp/airflow/hooks/cdw_hook.py
cloudera/cdp/airflow/model/__init__.py
cloudera/cdp/airflow/model/connection.py
cloudera/cdp/airflow/operators/__init__.py
cloudera/cdp/airflow/operators/cde_operator.py
cloudera/cdp/airflow/operators/cdw_operator.py
cloudera/cdp/airflow/sensors/__init__.py
cloudera/cdp/airflow/sensors/cdw_sensor.py
cloudera_airflow_provider-2.1.2.dist-info/DESCRIPTION.rst
cloudera_airflow_provider-2.1.2.dist-info/METADATA
cloudera_airflow_provider-2.1.2.dist-info/RECORD
cloudera_airflow_provider-2.1.2.dist-info/WHEEL
cloudera_airflow_provider-2.1.2.dist-info/entry_points.txt
cloudera_airflow_provider-2.1.2.dist-info/metadata.json
cloudera_airflow_provider-2.1.2.dist-info/top_level.txt
